[
  {
    "id": "AAPL",
    "name": "Apple Inc.",
    "logo": "https://logo.clearbit.com/apple.com",
    "currentPrice": 178.42,
    "change": 1.23,
    "changePercent": 0.69,
    "marketCap": "2.78T",
    "sector": "Technology",
    "priceHistory": [
      { "date": "2023-01-01", "price": 130.82, "volume": 71314992 },
      { "date": "2023-02-01", "price": 145.91, "volume": 54712321 },
      { "date": "2023-03-01", "price": 157.65, "volume": 62411896 },
      { "date": "2023-04-01", "price": 165.02, "volume": 47721456 },
      { "date": "2023-05-01", "price": 172.58, "volume": 51981334 },
      { "date": "2023-06-01", "price": 184.92, "volume": 59872145 },
      { "date": "2023-07-01", "price": 189.25, "volume": 48753692 },
      { "date": "2023-08-01", "price": 178.85, "volume": 63254789 },
      { "date": "2023-09-01", "price": 171.21, "volume": 57896523 },
      { "date": "2023-10-01", "price": 168.45, "volume": 52123456 },
      { "date": "2023-11-01", "price": 175.98, "volume": 49876543 },
      { "date": "2023-12-01", "price": 173.57, "volume": 61234567 },
      { "date": "2024-01-01", "price": 182.63, "volume": 58912345 },
      { "date": "2024-02-01", "price": 169.56, "volume": 67891234 },
      { "date": "2024-03-01", "price": 175.89, "volume": 53456789 },
      { "date": "2024-04-01", "price": 178.42, "volume": 55678912 }
    ]
  },
  {
    "id": "MSFT",
    "name": "Microsoft Corporation",
    "logo": "https://logo.clearbit.com/microsoft.com",
    "currentPrice": 413.72,
    "change": -2.78,
    "changePercent": -0.67,
    "marketCap": "3.07T",
    "sector": "Technology",
    "priceHistory": [
      { "date": "2023-01-01", "price": 248.12, "volume": 63214578 },
      { "date": "2023-02-01", "price": 251.43, "volume": 57698423 },
      { "date": "2023-03-01", "price": 267.58, "volume": 61234689 },
      { "date": "2023-04-01", "price": 285.76, "volume": 59874563 },
      { "date": "2023-05-01", "price": 310.65, "volume": 68791254 },
      { "date": "2023-06-01", "price": 335.85, "volume": 63214785 },
      { "date": "2023-07-01", "price": 345.24, "volume": 54632189 },
      { "date": "2023-08-01", "price": 322.93, "volume": 59871236 },
      { "date": "2023-09-01", "price": 347.85, "volume": 63214587 },
      { "date": "2023-10-01", "price": 359.92, "volume": 68912345 },
      { "date": "2023-11-01", "price": 375.03, "volume": 57896321 },
      { "date": "2023-12-01", "price": 381.24, "volume": 61234587 },
      { "date": "2024-01-01", "price": 395.63, "volume": 72145896 },
      { "date": "2024-02-01", "price": 402.56, "volume": 68523147 },
      { "date": "2024-03-01", "price": 417.88, "volume": 63214587 },
      { "date": "2024-04-01", "price": 413.72, "volume": 59871236 }
    ]
  },
  {
    "id": "AMZN",
    "name": "Amazon.com Inc.",
    "logo": "https://logo.clearbit.com/amazon.com",
    "currentPrice": 178.12,
    "change": 5.82,
    "changePercent": 3.38,
    "marketCap": "1.84T",
    "sector": "Consumer Cyclical",
    "priceHistory": [
      { "date": "2023-01-01", "price": 98.12, "volume": 89654123 },
      { "date": "2023-02-01", "price": 103.39, "volume": 78523169 },
      { "date": "2023-03-01", "price": 112.91, "volume": 85236914 },
      { "date": "2023-04-01", "price": 109.56, "volume": 79845612 },
      { "date": "2023-05-01", "price": 120.58, "volume": 82365419 },
      { "date": "2023-06-01", "price": 130.15, "volume": 85964123 },
      { "date": "2023-07-01", "price": 135.36, "volume": 79845612 },
      { "date": "2023-08-01", "price": 140.64, "volume": 85236914 },
      { "date": "2023-09-01", "price": 145.98, "volume": 75365214 },
      { "date": "2023-10-01", "price": 155.12, "volume": 85236914 },
      { "date": "2023-11-01", "price": 150.63, "volume": 82365419 },
      { "date": "2023-12-01", "price": 158.72, "volume": 89654123 },
      { "date": "2024-01-01", "price": 165.42, "volume": 92145623 },
      { "date": "2024-02-01", "price": 172.89, "volume": 85236914 },
      { "date": "2024-03-01", "price": 168.14, "volume": 82365419 },
      { "date": "2024-04-01", "price": 178.12, "volume": 85236914 }
    ]
  },
  {
    "id": "GOOGL",
    "name": "Alphabet Inc.",
    "logo": "https://logo.clearbit.com/google.com",
    "currentPrice": 156.28,
    "change": 0.97,
    "changePercent": 0.62,
    "marketCap": "1.96T",
    "sector": "Technology",
    "priceHistory": [
      { "date": "2023-01-01", "price": 95.78, "volume": 72365418 },
      { "date": "2023-02-01", "price": 101.43, "volume": 68974512 },
      { "date": "2023-03-01", "price": 109.46, "volume": 72365418 },
      { "date": "2023-04-01", "price": 112.97, "volume": 65893247 },
      { "date": "2023-05-01", "price": 118.29, "volume": 68974512 },
      { "date": "2023-06-01", "price": 124.06, "volume": 72365418 },
      { "date": "2023-07-01", "price": 131.86, "volume": 68974512 },
      { "date": "2023-08-01", "price": 126.67, "volume": 72365418 },
      { "date": "2023-09-01", "price": 133.09, "volume": 68974512 },
      { "date": "2023-10-01", "price": 139.72, "volume": 72365418 },
      { "date": "2023-11-01", "price": 133.29, "volume": 65893247 },
      { "date": "2023-12-01", "price": 139.69, "volume": 72365418 },
      { "date": "2024-01-01", "price": 145.92, "volume": 68974512 },
      { "date": "2024-02-01", "price": 151.77, "volume": 72365418 },
      { "date": "2024-03-01", "price": 156.57, "volume": 65893247 },
      { "date": "2024-04-01", "price": 156.28, "volume": 72365418 }
    ]
  },
  {
    "id": "TSLA",
    "name": "Tesla, Inc.",
    "logo": "https://logo.clearbit.com/tesla.com",
    "currentPrice": 188.14,
    "change": -4.82,
    "changePercent": -2.5,
    "marketCap": "598.96B",
    "sector": "Automotive",
    "priceHistory": [
      { "date": "2023-01-01", "price": 123.18, "volume": 156478293 },
      { "date": "2023-02-01", "price": 197.79, "volume": 182365418 },
      { "date": "2023-03-01", "price": 189.98, "volume": 162589743 },
      { "date": "2023-04-01", "price": 160.31, "volume": 145632789 },
      { "date": "2023-05-01", "price": 190.81, "volume": 152698473 },
      { "date": "2023-06-01", "price": 257.24, "volume": 172589634 },
      { "date": "2023-07-01", "price": 272.51, "volume": 152698473 },
      { "date": "2023-08-01", "price": 238.10, "volume": 162589743 },
      { "date": "2023-09-01", "price": 240.50, "volume": 152698473 },
      { "date": "2023-10-01", "price": 215.52, "volume": 162589743 },
      { "date": "2023-11-01", "price": 240.68, "volume": 145632789 },
      { "date": "2023-12-01", "price": 252.54, "volume": 162589743 },
      { "date": "2024-01-01", "price": 209.14, "volume": 172589634 },
      { "date": "2024-02-01", "price": 194.77, "volume": 152698473 },
      { "date": "2024-03-01", "price": 176.85, "volume": 162589743 },
      { "date": "2024-04-01", "price": 188.14, "volume": 156478293 }
    ]
  },
  {
    "id": "META",
    "name": "Meta Platforms Inc.",
    "logo": "https://logo.clearbit.com/meta.com",
    "currentPrice": 493.50,
    "change": 7.85,
    "changePercent": 1.61,
    "marketCap": "1.26T",
    "sector": "Technology",
    "priceHistory": [
      { "date": "2023-01-01", "price": 124.74, "volume": 65236987 },
      { "date": "2023-02-01", "price": 169.15, "volume": 75896432 },
      { "date": "2023-03-01", "price": 207.84, "volume": 85236941 },
      { "date": "2023-04-01", "price": 224.95, "volume": 65236987 },
      { "date": "2023-05-01", "price": 253.00, "volume": 75896432 },
      { "date": "2023-06-01", "price": 286.02, "volume": 85236941 },
      { "date": "2023-07-01", "price": 325.48, "volume": 65236987 },
      { "date": "2023-08-01", "price": 300.21, "volume": 85236941 },
      { "date": "2023-09-01", "price": 305.07, "volume": 75896432 },
      { "date": "2023-10-01", "price": 314.60, "volume": 85236941 },
      { "date": "2023-11-01", "price": 341.49, "volume": 65236987 },
      { "date": "2023-12-01", "price": 351.77, "volume": 75896432 },
      { "date": "2024-01-01", "price": 394.14, "volume": 85236941 },
      { "date": "2024-02-01", "price": 469.07, "volume": 75896432 },
      { "date": "2024-03-01", "price": 486.18, "volume": 65236987 },
      { "date": "2024-04-01", "price": 493.50, "volume": 75896432 }
    ]
  }
] 